thumbtack_client/DuplicateMountAttemptException.py
thumbtack_client/MountedDiskImage.py
thumbtack_client/MountedDiskImageVolume.py
thumbtack_client/ThumbtackClientException.py
thumbtack_client/__init__.py
thumbtack_client-0.4.0.dist-info/LICENSE
thumbtack_client-0.4.0.dist-info/METADATA
thumbtack_client-0.4.0.dist-info/WHEEL
thumbtack_client-0.4.0.dist-info/top_level.txt
thumbtack_client-0.4.0.dist-info/RECORD
